qwiic_as7343.py
sparkfun_qwiic_as7343-1.0.0.dist-info/licenses/LICENSE
sparkfun_qwiic_as7343-1.0.0.dist-info/METADATA
sparkfun_qwiic_as7343-1.0.0.dist-info/WHEEL
sparkfun_qwiic_as7343-1.0.0.dist-info/top_level.txt
sparkfun_qwiic_as7343-1.0.0.dist-info/RECORD
