Metadata-Version: 2.4
Name: sparkfun_qwiic_as7343
Version: 1.0.0
Summary: SparkFun Electronics Qwiic AS7343
Author-email: Sparkfun Electronics <info@sparkfun.com>
Project-URL: homepage, https://www.sparkfun.com/products/TODO
Keywords: electronics, maker
Classifier: Development Status :: 5 - Production/Stable
Classifier: Intended Audience :: Developers
Classifier: Topic :: Software Development :: Build Tools
Classifier: License :: OSI Approved :: MIT License
Classifier: Programming Language :: Python :: 3.5
Classifier: Programming Language :: Python :: 3.6
Classifier: Programming Language :: Python :: 3.7
Classifier: Programming Language :: Python :: 3.8
Classifier: Programming Language :: Python :: 3.9
Classifier: Programming Language :: Python :: 3.10
Classifier: Programming Language :: Python :: 3.11
Classifier: Programming Language :: Python :: 3.12
Classifier: Programming Language :: Python :: 3.13
Classifier: Programming Language :: Python :: 3.14
Classifier: Programming Language :: Python :: Implementation :: MicroPython
License-File: LICENSE
Requires-Dist: sparkfun_qwiic_i2c
Dynamic: license-file
